pyprep/__init__.py
pyprep/find_noisy_channels.py
pyprep/prep_pipeline.py
pyprep/ransac.py
pyprep/reference.py
pyprep/removeTrend.py
pyprep/utils.py
pyprep-0.5.0.dist-info/METADATA
pyprep-0.5.0.dist-info/WHEEL
pyprep-0.5.0.dist-info/licenses/LICENSE
pyprep-0.5.0.dist-info/RECORD
