Metadata-Version: 2.4
Name: pyprep
Version: 0.5.0
Summary: PyPREP: A Python implementation of the preprocessing pipeline (PREP) for EEG data.
Project-URL: Bug Tracker, https://github.com/sappelhoff/pyprep/issues/
Project-URL: Documentation, https://pyprep.readthedocs.io/en/latest
Project-URL: Homepage, https://pyprep.readthedocs.io/en/latest
Project-URL: Source Code, https://github.com/sappelhoff/pyprep
Author: PyPREP developers
Maintainer-email: Stefan Appelhoff <stefan.appelhoff@mailbox.org>
License: MIT License
License-File: LICENSE
Keywords: EEG,artifact,data,electroencephalography,mne,neuroimaging,neuroscience,preprocessing,python
Classifier: Intended Audience :: Developers
Classifier: Intended Audience :: Science/Research
Classifier: License :: OSI Approved
Classifier: Operating System :: MacOS
Classifier: Operating System :: Microsoft :: Windows
Classifier: Operating System :: POSIX :: Linux
Classifier: Programming Language :: Python
Classifier: Programming Language :: Python :: 3.9
Classifier: Programming Language :: Python :: 3.10
Classifier: Programming Language :: Python :: 3.11
Classifier: Programming Language :: Python :: 3.12
Classifier: Topic :: Scientific/Engineering
Requires-Python: >=3.9
Requires-Dist: mne>=1.3.0
Requires-Dist: numpy>=1.20.2
Requires-Dist: psutil>=5.4.3
Requires-Dist: scipy>=1.6.3
Provides-Extra: dev
Requires-Dist: build; extra == 'dev'
Requires-Dist: intersphinx-registry; extra == 'dev'
Requires-Dist: ipykernel; extra == 'dev'
Requires-Dist: ipython; extra == 'dev'
Requires-Dist: matplotlib; extra == 'dev'
Requires-Dist: numpydoc; extra == 'dev'
Requires-Dist: pre-commit; extra == 'dev'
Requires-Dist: pydata-sphinx-theme; extra == 'dev'
Requires-Dist: pytest; extra == 'dev'
Requires-Dist: pytest-cov; extra == 'dev'
Requires-Dist: pytest-sugar; extra == 'dev'
Requires-Dist: ruff; extra == 'dev'
Requires-Dist: sphinx; extra == 'dev'
Requires-Dist: sphinx-copybutton; extra == 'dev'
Requires-Dist: sphinx-gallery; extra == 'dev'
Requires-Dist: twine; extra == 'dev'
Provides-Extra: docs
Requires-Dist: intersphinx-registry; extra == 'docs'
Requires-Dist: matplotlib; extra == 'docs'
Requires-Dist: numpydoc; extra == 'docs'
Requires-Dist: pydata-sphinx-theme; extra == 'docs'
Requires-Dist: sphinx; extra == 'docs'
Requires-Dist: sphinx-copybutton; extra == 'docs'
Requires-Dist: sphinx-gallery; extra == 'docs'
Provides-Extra: test
Requires-Dist: build; extra == 'test'
Requires-Dist: matplotlib; extra == 'test'
Requires-Dist: pre-commit; extra == 'test'
Requires-Dist: pytest; extra == 'test'
Requires-Dist: pytest-cov; extra == 'test'
Requires-Dist: pytest-sugar; extra == 'test'
Requires-Dist: ruff; extra == 'test'
Requires-Dist: twine; extra == 'test'
